Metadata-Version: 2.1
Name: templategen
Version: 0.0.2
Summary: Souce code generator from a given template
Home-page: https://github.com/TediCreations/templategen
Author: Kanelis Elias
Author-email: hkanelhs@yahoo.gr
License: MIT
Download-URL: https://github.com/TediCreations/templategen/archive/Unknown.tar.gz
Keywords: build,make,util
Platform: UNKNOWN
Classifier: Development Status :: 3 - Alpha
Classifier: Intended Audience :: Developers
Classifier: Topic :: Software Development :: Build Tools
Classifier: License :: OSI Approved :: GNU General Public License v3 (GPLv3)
Classifier: Programming Language :: Python :: 3
Classifier: Programming Language :: Python :: 3.6
License-File: LICENSE
